langraph_api/__init__.py
langraph_api/config.py
langraph_api/docs_builder.py
langraph_api/files/swagger.html
langraph_api/func_app_builder/__init__.py
langraph_api/func_app_builder/blueprint_builder.py
langraph_api/func_app_builder/create_app.py
langraph_api/func_app_builder/func_app_builder.py
langraph_api/graph_endpoints/__init__.py
langraph_api/graph_endpoints/graph_executor_factory.py
langraph_api/graph_endpoints/graph_executor_service.py
langraph_api/graph_endpoints/registry.py
langraph_api/graph_helpers/__init__.py
langraph_api/graph_helpers/call_subgraph.py
langraph_api/graph_helpers/graph_builder_helpers.py
langraph_api/graph_helpers/wrappers.py
langraph_api/logger.py
langraph_api/prompt_templates/clean_output.py
langraph_api/prompt_templates/finn.py
langraph_api/settings.py
langraph_api/types.py
langraph_api/yml_config/__init__.py
langraph_api/yml_config/loader.py
langraph_api/yml_config/models.py
langraph_api-0.1.4.dist-info/METADATA
langraph_api-0.1.4.dist-info/WHEEL
langraph_api-0.1.4.dist-info/RECORD
